{
  "next_rev_id": 2,
  "next_dr_id": 2,
  "tickets": [
    {
      "id": "REV-001",
      "kind": "comment",
      "modelId": "f7ad3c372e074ea69500eb87fba55a50",
      "title": "Increase thickness of Bracket",
      "description": "stupid stress engineeris",
      "type": "comment",
      "priority": "medium",
      "status": "open",
      "author": "Adeel",
      "tag": "stress",
      "pin": {
        "position": [
          33.865050623171555,
          364.9498265292953,
          -37.9347364168716
        ],
        "normal": [
          0.0,
          0.710310406645523,
          0.7038885751389008
        ],
        "cameraState": {
          "position": [
            117.8426794294109,
            486.3383764508953,
            117.84267942941091
          ],
          "target": [
            0,
            368.4956970214844,
            0
          ]
        }
      },
      "replies": [],
      "createdAt": "2026-01-31T05:04:29.374972+00:00",
      "updatedAt": "2026-01-31T05:04:29.374972+00:00"
    }
  ],
  "design_reviews": [
    {
      "id": "DR-001",
      "kind": "design_review",
      "modelId": "f7ad3c372e074ea69500eb87fba55a50",
      "templateId": "mfg",
      "templateName": "Manufacturing Review",
      "title": "Design for Assembly",
      "author": "Adeel",
      "status": "failed",
      "pin": {
        "position": [
          1.4808984943119867,
          373.271721353561,
          -15.90140866310503
        ],
        "normal": [
          0.07198677216049162,
          0.9942648145844597,
          -0.07909097997397536
        ],
        "cameraState": {
          "position": [
            117.8426794294109,
            486.3383764508953,
            117.84267942941091
          ],
          "target": [
            0,
            368.4956970214844,
            0
          ]
        }
      },
      "checklist": [
        {
          "id": "item-1",
          "text": "Wall thickness is uniform and meets minimum for chosen process",
          "status": "pass",
          "note": ""
        },
        {
          "id": "item-2",
          "text": "Draft angles are sufficient for mold release (1-3 degrees minimum)",
          "status": "fail",
          "note": ""
        },
        {
          "id": "item-3",
          "text": "Undercuts are eliminated or can be formed with simple side actions",
          "status": "pending",
          "note": ""
        },
        {
          "id": "item-4",
          "text": "Corner radii are adequate to prevent stress concentration",
          "status": "pending",
          "note": ""
        },
        {
          "id": "item-5",
          "text": "Tolerances are achievable with the intended manufacturing process",
          "status": "pending",
          "note": ""
        },
        {
          "id": "item-6",
          "text": "Material selection is compatible with the manufacturing method",
          "status": "pending",
          "note": ""
        },
        {
          "id": "item-7",
          "text": "Surface finish requirements are specified and achievable",
          "status": "pending",
          "note": ""
        },
        {
          "id": "item-8",
          "text": "Part can be fixtured/held securely during machining operations",
          "status": "pending",
          "note": ""
        }
      ],
      "replies": [],
      "createdAt": "2026-01-31T05:04:51.122156+00:00",
      "updatedAt": "2026-01-31T05:04:59.455832+00:00"
    }
  ]
}